dummy.cp37-win_amd64.pyd
example_nim_pkg/__init__.py
example_nim_pkg/mymodule.pyd
example_nim_pkg_stever-0.0.3.dist-info/LICENSE
example_nim_pkg_stever-0.0.3.dist-info/METADATA
example_nim_pkg_stever-0.0.3.dist-info/WHEEL
example_nim_pkg_stever-0.0.3.dist-info/top_level.txt
example_nim_pkg_stever-0.0.3.dist-info/RECORD
