Metadata-Version: 2.1
Name: example-nim-pkg-stever
Version: 0.0.3
Summary: A small example package with Nim module
Home-page: https://github.com/stever/example-nim-pip-pkg
Author: Steven Robertson
Author-email: stever@hey.com
License: UNKNOWN
Platform: UNKNOWN
Classifier: Programming Language :: Python :: 3
Classifier: License :: OSI Approved :: MIT License
Classifier: Operating System :: OS Independent
